tinyai/__init__.py
tinyai/train.py
tinyai/data/__init__.py
tinyai/data/dataloaders.py
tinyai/data/datasets.py
tinyai/data/tokenizers.py
tinyai/models/__init__.py
tinyai/models/base.py
tinyai/models/llm.py
tinyai/models/vision.py
tinyai/training/__init__.py
tinyai/training/optimizer.py
tinyai/training/trainer.py
tinyai/utils/__init__.py
tinyai/utils/logging.py
tinyai/utils/lr_finder.py
tinyai/utils/metrics.py
tinyaicli-0.1.0.dist-info/licenses/LICENSE
tinyaicli-0.1.0.dist-info/METADATA
tinyaicli-0.1.0.dist-info/WHEEL
tinyaicli-0.1.0.dist-info/entry_points.txt
tinyaicli-0.1.0.dist-info/top_level.txt
tinyaicli-0.1.0.dist-info/RECORD
