Metadata-Version: 2.4
Name: tinyaicli
Version: 0.1.0
Summary: A CLI tool for training small LLMs and vision models with reproducible research
Home-page: https://github.com/nheinstein/tinyai
Author: Nathan Heinstein
Author-email: nathan.heinstein@dal.ca
Classifier: Development Status :: 3 - Alpha
Classifier: Intended Audience :: Developers
Classifier: Intended Audience :: Science/Research
Classifier: License :: OSI Approved :: MIT License
Classifier: Operating System :: OS Independent
Classifier: Programming Language :: Python :: 3
Classifier: Programming Language :: Python :: 3.8
Classifier: Programming Language :: Python :: 3.9
Classifier: Programming Language :: Python :: 3.10
Classifier: Programming Language :: Python :: 3.11
Classifier: Topic :: Scientific/Engineering :: Artificial Intelligence
Classifier: Topic :: Software Development :: Libraries :: Python Modules
Requires-Python: >=3.8
License-File: LICENSE
Requires-Dist: torch>=2.0.0
Requires-Dist: torchvision>=0.15.0
Requires-Dist: torchaudio>=2.0.0
Requires-Dist: hydra-core>=1.3.0
Requires-Dist: hydra-colorlog>=1.2.0
Requires-Dist: wandb>=0.15.0
Requires-Dist: omegaconf>=2.3.0
Requires-Dist: datasets>=2.14.0
Requires-Dist: transformers>=4.30.0
Requires-Dist: tokenizers>=0.13.0
Requires-Dist: numpy>=1.24.0
Requires-Dist: pandas>=2.0.0
Requires-Dist: matplotlib>=3.7.0
Requires-Dist: seaborn>=0.12.0
Requires-Dist: tqdm>=4.65.0
Requires-Dist: pyyaml>=6.0
Requires-Dist: click>=8.1.0
Requires-Dist: rich>=13.0.0
Requires-Dist: tensorboard>=2.13.0
Requires-Dist: pillow>=10.0.0
Requires-Dist: scikit-learn>=1.3.0
Requires-Dist: accelerate>=0.20.0
Requires-Dist: peft>=0.4.0
Requires-Dist: bitsandbytes>=0.41.0
Dynamic: author
Dynamic: author-email
Dynamic: classifier
Dynamic: description
Dynamic: description-content-type
Dynamic: home-page
Dynamic: license-file
Dynamic: requires-dist
Dynamic: requires-python
Dynamic: summary
